{"nb_somersaults": 1, "model_path": "", "final_time": 1, "final_time_margin": 0.1, "position": "straight", "sport_type": "diving", "preferred_twist_side": "left", "somersaults_info": [{"nb_shooting_points": 24, "nb_half_twists": 0, "duration": 1, "objectives": [{"objective_type": "lagrange", "penalty_type": "MINIMIZE_CONTROL", "nodes": "all_shooting", "quadratic": false, "expand": false, "target": null, "derivative": true, "integration_rule": "midpoint", "multi_thread": true, "weight": 100.0, "arguments": {"key": {"value": "tau", "type": "string"}}}, {"objective_type": "mayer", "penalty_type": "MINIMIZE_TIME", "nodes": "end", "quadratic": true, "expand": true, "target": null, "derivative": false, "integration_rule": "rectangle_left", "multi_thread": false, "weight": 1.0, "arguments": {"min_bound": {"value": 0.9, "type": "float"}, "max_bound": {"value": 1.1, "type": "float"}}}], "constraints": []}]}